LICENSE
MANIFEST.in
README.md
setup.cfg
setup.py
stdeb.cfg
./aedir/__about__.py
./aedir/__init__.py
./aedir/models.py
./aedir/process.py
./aedir/sync.py
./aedir/test.py
aedir.egg-info/PKG-INFO
aedir.egg-info/SOURCES.txt
aedir.egg-info/dependency_links.txt
aedir.egg-info/not-zip-safe
aedir.egg-info/requires.txt
aedir.egg-info/top_level.txt
tests/__init__.py
tests/ae-dir-init.ldif
tests/ae-dir-process-test.cfg
tests/ae-logging.conf
tests/ldap_aedir_test.conf
tests/single-provider.json
tests/test_aedir_models.py
tests/test_aedir_process.py
tests/test_aedir_simple_functions.py
tests/test_aedirobject.py
tests/test_message.txt
tests/sasl2/slapd.conf
tests/tls/ca-chain.pem
tests/tls/localhost.crt
tests/tls/localhost.key
tests/tls/slapd-dhparams.pem
tests/tls/test-client.crt
tests/tls/test-client.key